fio_planet/__init__.py
fio_planet/cli.py
fio_planet/errors.py
fio_planet/features.py
fio_planet/snuggs.py
fio_planet-1.0.1.dist-info/entry_points.txt
fio_planet-1.0.1.dist-info/LICENSE
fio_planet-1.0.1.dist-info/WHEEL
fio_planet-1.0.1.dist-info/METADATA
fio_planet-1.0.1.dist-info/RECORD
