Metadata-Version: 2.1
Name: fio_planet
Version: 1.0.1
Summary: fio_planet: Fiona CLI plugins from Planet Labs.
Keywords: GeoJSON,GIS,CLI
Author: Sean Gillies
Maintainer-email: Planet Developer Relations <developers@planet.com>
Requires-Python: >=3.7
Classifier: Development Status :: 4 - Beta
Classifier: Programming Language :: Python :: 3
Classifier: License :: OSI Approved :: Apache Software License
Requires-Dist: click
Requires-Dist: fiona
Requires-Dist: pyparsing>=3.0
Requires-Dist: shapely>=2.0
Requires-Dist: mkdocs ; extra == "docs"
Requires-Dist: mkdocs-material ; extra == "docs"
Requires-Dist: mkdocs-click ; extra == "docs"
Requires-Dist: mkdocstrings ; extra == "docs"
Requires-Dist: pytest-cov ; extra == "test"
Provides-Extra: docs
Provides-Extra: test
